{
  "pages": [
    {
      "page_index": 0,
      "width": 1600,
      "height": 2200,
      "tokens": [
        {
          "text": "IDENTITY",
          "bbox": [
            606,
            70,
            853,
            107
          ],
          "line_id": 0,
          "block_id": 0,
          "conf": 0.9334
        },
        {
          "text": "CARD",
          "bbox": [
            867,
            70,
            991,
            109
          ],
          "line_id": 0,
          "block_id": 0,
          "conf": 0.9793
        },
        {
          "text": "DOCUMENT",
          "bbox": [
            640,
            134,
            754,
            149
          ],
          "line_id": 1,
          "block_id": 1,
          "conf": 0.9559
        },
        {
          "text": "—",
          "bbox": [
            764,
            133,
            778,
            151
          ],
          "line_id": 1,
          "block_id": 1,
          "conf": 0.8968
        },
        {
          "text": "USE",
          "bbox": [
            1039,
            133,
            1086,
            151
          ],
          "line_id": 1,
          "block_id": 1,
          "conf": 0.9031
        },
        {
          "text": "NOT",
          "bbox": [
            784,
            136,
            829,
            151
          ],
          "line_id": 1,
          "block_id": 1,
          "conf": 0.9086
        },
        {
          "text": "OFFICIAL",
          "bbox": [
            516,
            137,
            629,
            152
          ],
          "line_id": 1,
          "block_id": 1,
          "conf": 0.8559
        },
        {
          "text": "FOR",
          "bbox": [
            835,
            137,
            881,
            152
          ],
          "line_id": 1,
          "block_id": 1,
          "conf": 0.8643
        },
        {
          "text": "COMMERCIAL",
          "bbox": [
            888,
            136,
            1031,
            153
          ],
          "line_id": 1,
          "block_id": 1,
          "conf": 0.8685
        },
        {
          "text": "PH241948",
          "bbox": [
            420,
            210,
            562,
            233
          ],
          "line_id": 2,
          "block_id": 3,
          "conf": 0.9854
        },
        {
          "text": "ID",
          "bbox": [
            81,
            212,
            113,
            233
          ],
          "line_id": 2,
          "block_id": 3,
          "conf": 0.8341
        },
        {
          "text": "Number:",
          "bbox": [
            122,
            212,
            235,
            234
          ],
          "line_id": 2,
          "block_id": 3,
          "conf": 0.8645
        },
        {
          "text": "Name:",
          "bbox": [
            149,
            288,
            227,
            312
          ],
          "line_id": 3,
          "block_id": 4,
          "conf": 0.9877
        },
        {
          "text": "Full",
          "bbox": [
            81,
            292,
            143,
            313
          ],
          "line_id": 3,
          "block_id": 4,
          "conf": 0.9039
        },
        {
          "text": "Ryan",
          "bbox": [
            551,
            290,
            619,
            318
          ],
          "line_id": 3,
          "block_id": 4,
          "conf": 0.8803
        },
        {
          "text": "Angelica",
          "bbox": [
            418,
            290,
            546,
            319
          ],
          "line_id": 3,
          "block_id": 4,
          "conf": 0.8298
        },
        {
          "text": "1981-09-01",
          "bbox": [
            421,
            370,
            575,
            390
          ],
          "line_id": 4,
          "block_id": 5,
          "conf": 0.9073
        },
        {
          "text": "Date",
          "bbox": [
            80,
            372,
            135,
            390
          ],
          "line_id": 4,
          "block_id": 5,
          "conf": 0.9528
        },
        {
          "text": "of",
          "bbox": [
            141,
            371,
            168,
            393
          ],
          "line_id": 4,
          "block_id": 5,
          "conf": 0.9022
        },
        {
          "text": "Birth:",
          "bbox": [
            174,
            372,
            256,
            392
          ],
          "line_id": 4,
          "block_id": 5,
          "conf": 0.9031
        },
        {
          "text": "2010-08-21",
          "bbox": [
            420,
            448,
            577,
            471
          ],
          "line_id": 5,
          "block_id": 6,
          "conf": 0.8439
        },
        {
          "text": "Date:",
          "bbox": [
            161,
            449,
            233,
            471
          ],
          "line_id": 5,
          "block_id": 6,
          "conf": 0.85
        },
        {
          "text": "Issue",
          "bbox": [
            82,
            449,
            153,
            474
          ],
          "line_id": 5,
          "block_id": 6,
          "conf": 0.9597
        },
        {
          "text": "2020-08-21",
          "bbox": [
            422,
            532,
            575,
            554
          ],
          "line_id": 6,
          "block_id": 7,
          "conf": 0.8784
        },
        {
          "text": "Date:",
          "bbox": [
            170,
            529,
            243,
            560
          ],
          "line_id": 6,
          "block_id": 7,
          "conf": 0.8701
        },
        {
          "text": "Expiry",
          "bbox": [
            79,
            530,
            164,
            560
          ],
          "line_id": 6,
          "block_id": 7,
          "conf": 0.8725
        },
        {
          "text": "United",
          "bbox": [
            422,
            608,
            506,
            631
          ],
          "line_id": 7,
          "block_id": 8,
          "conf": 0.8708
        },
        {
          "text": "States",
          "bbox": [
            513,
            609,
            601,
            633
          ],
          "line_id": 7,
          "block_id": 8,
          "conf": 0.9739
        },
        {
          "text": "Country:",
          "bbox": [
            187,
            608,
            297,
            638
          ],
          "line_id": 7,
          "block_id": 8,
          "conf": 0.9675
        },
        {
          "text": "Issuing",
          "bbox": [
            81,
            609,
            177,
            638
          ],
          "line_id": 7,
          "block_id": 8,
          "conf": 0.8469
        },
        {
          "text": "UNITEDSTATES",
          "bbox": [
            422,
            688,
            599,
            714
          ],
          "line_id": 8,
          "block_id": 9,
          "conf": 0.8647
        },
        {
          "text": "NATIONALITY:",
          "bbox": [
            81,
            689,
            230,
            719
          ],
          "line_id": 8,
          "block_id": 9,
          "conf": 0.8382
        },
        {
          "text": "Sex:",
          "bbox": [
            82,
            772,
            141,
            791
          ],
          "line_id": 9,
          "block_id": 10,
          "conf": 0.8333
        },
        {
          "text": "F",
          "bbox": [
            420,
            772,
            438,
            791
          ],
          "line_id": 9,
          "block_id": 10,
          "conf": 0.9317
        },
        {
          "text": "property",
          "bbox": [
            741,
            888,
            821,
            909
          ],
          "line_id": 10,
          "block_id": 12,
          "conf": 0.91
        },
        {
          "text": "card",
          "bbox": [
            586,
            889,
            625,
            910
          ],
          "line_id": 10,
          "block_id": 12,
          "conf": 0.8412
        },
        {
          "text": "authority.",
          "bbox": [
            960,
            890,
            1061,
            909
          ],
          "line_id": 10,
          "block_id": 12,
          "conf": 0.9317
        },
        {
          "text": "of",
          "bbox": [
            824,
            890,
            847,
            910
          ],
          "line_id": 10,
          "block_id": 12,
          "conf": 0.9646
        },
        {
          "text": "This",
          "bbox": [
            541,
            890,
            577,
            911
          ],
          "line_id": 10,
          "block_id": 12,
          "conf": 0.9743
        },
        {
          "text": "issuing",
          "bbox": [
            884,
            890,
            956,
            911
          ],
          "line_id": 10,
          "block_id": 12,
          "conf": 0.8799
        },
        {
          "text": "the",
          "bbox": [
            852,
            892,
            881,
            910
          ],
          "line_id": 10,
          "block_id": 12,
          "conf": 0.8481
        },
        {
          "text": "remains",
          "bbox": [
            630,
            892,
            701,
            912
          ],
          "line_id": 10,
          "block_id": 12,
          "conf": 0.948
        },
        {
          "text": "the",
          "bbox": [
            706,
            892,
            734,
            912
          ],
          "line_id": 10,
          "block_id": 12,
          "conf": 0.9605
        }
      ]
    }
  ]
}
