{
  "pages": [
    {
      "page_index": 0,
      "width": 1600,
      "height": 2200,
      "tokens": [
        {
          "text": "Sterling",
          "bbox": [
            579,
            68,
            777,
            116
          ],
          "line_id": 0,
          "block_id": 0,
          "conf": 0.8912
        },
        {
          "text": "Goods",
          "bbox": [
            789,
            70,
            908,
            116
          ],
          "line_id": 0,
          "block_id": 0,
          "conf": 0.963
        },
        {
          "text": "Ltd.",
          "bbox": [
            920,
            70,
            1019,
            117
          ],
          "line_id": 0,
          "block_id": 0,
          "conf": 0.9417
        },
        {
          "text": "PAYMENT",
          "bbox": [
            632,
            129,
            795,
            156
          ],
          "line_id": 1,
          "block_id": 1,
          "conf": 0.9109
        },
        {
          "text": "RECEIPT",
          "bbox": [
            803,
            129,
            972,
            156
          ],
          "line_id": 1,
          "block_id": 1,
          "conf": 0.8819
        },
        {
          "text": "Sender",
          "bbox": [
            79,
            204,
            164,
            226
          ],
          "line_id": 2,
          "block_id": 3,
          "conf": 0.9065
        },
        {
          "text": "Donald",
          "bbox": [
            82,
            238,
            175,
            261
          ],
          "line_id": 3,
          "block_id": 3,
          "conf": 0.8276
        },
        {
          "text": "Bennett",
          "bbox": [
            179,
            241,
            290,
            264
          ],
          "line_id": 3,
          "block_id": 3,
          "conf": 0.9036
        },
        {
          "text": "Date",
          "bbox": [
            78,
            289,
            133,
            309
          ],
          "line_id": 4,
          "block_id": 4,
          "conf": 0.8337
        },
        {
          "text": "2025-07-11",
          "bbox": [
            299,
            292,
            430,
            310
          ],
          "line_id": 4,
          "block_id": 4,
          "conf": 0.8829
        },
        {
          "text": "ID",
          "bbox": [
            128,
            323,
            151,
            342
          ],
          "line_id": 5,
          "block_id": 5,
          "conf": 0.8317
        },
        {
          "text": "Ref",
          "bbox": [
            82,
            327,
            118,
            344
          ],
          "line_id": 5,
          "block_id": 5,
          "conf": 0.9457
        },
        {
          "text": "TRX-900968",
          "bbox": [
            299,
            326,
            446,
            346
          ],
          "line_id": 5,
          "block_id": 5,
          "conf": 0.8657
        },
        {
          "text": "PRICE",
          "bbox": [
            1201,
            394,
            1280,
            412
          ],
          "line_id": 6,
          "block_id": 7,
          "conf": 0.9709
        },
        {
          "text": "ITEM",
          "bbox": [
            80,
            396,
            143,
            414
          ],
          "line_id": 6,
          "block_id": 7,
          "conf": 0.8504
        },
        {
          "text": "QTY",
          "bbox": [
            900,
            396,
            955,
            417
          ],
          "line_id": 6,
          "block_id": 7,
          "conf": 0.8795
        },
        {
          "text": "Item",
          "bbox": [
            78,
            453,
            137,
            477
          ],
          "line_id": 7,
          "block_id": 9,
          "conf": 0.953
        },
        {
          "text": "A",
          "bbox": [
            145,
            454,
            160,
            476
          ],
          "line_id": 7,
          "block_id": 9,
          "conf": 0.877
        },
        {
          "text": "1",
          "bbox": [
            899,
            457,
            918,
            474
          ],
          "line_id": 7,
          "block_id": 9,
          "conf": 0.9831
        },
        {
          "text": "375",
          "bbox": [
            1199,
            456,
            1243,
            477
          ],
          "line_id": 7,
          "block_id": 9,
          "conf": 0.9454
        },
        {
          "text": "5.37",
          "bbox": [
            1243,
            456,
            1302,
            477
          ],
          "line_id": 7,
          "block_id": 9,
          "conf": 0.8912
        },
        {
          "text": "1",
          "bbox": [
            899,
            505,
            918,
            525
          ],
          "line_id": 8,
          "block_id": 10,
          "conf": 0.92
        },
        {
          "text": "19.02",
          "bbox": [
            1200,
            509,
            1272,
            525
          ],
          "line_id": 8,
          "block_id": 10,
          "conf": 0.8763
        },
        {
          "text": "Service",
          "bbox": [
            80,
            506,
            182,
            531
          ],
          "line_id": 8,
          "block_id": 10,
          "conf": 0.8788
        },
        {
          "text": "Charge",
          "bbox": [
            187,
            509,
            275,
            533
          ],
          "line_id": 8,
          "block_id": 10,
          "conf": 0.826
        },
        {
          "text": "3755.37",
          "bbox": [
            1201,
            590,
            1304,
            609
          ],
          "line_id": 9,
          "block_id": 12,
          "conf": 0.8991
        },
        {
          "text": "Subtotal",
          "bbox": [
            79,
            588,
            185,
            612
          ],
          "line_id": 9,
          "block_id": 12,
          "conf": 0.8514
        },
        {
          "text": "Tax",
          "bbox": [
            80,
            626,
            128,
            646
          ],
          "line_id": 10,
          "block_id": 13,
          "conf": 0.9106
        },
        {
          "text": "245.92",
          "bbox": [
            1198,
            627,
            1290,
            649
          ],
          "line_id": 10,
          "block_id": 13,
          "conf": 0.9125
        },
        {
          "text": "1488.62",
          "bbox": [
            1267,
            688,
            1406,
            712
          ],
          "line_id": 11,
          "block_id": 15,
          "conf": 0.9871
        },
        {
          "text": "GBP",
          "bbox": [
            1198,
            690,
            1260,
            712
          ],
          "line_id": 11,
          "block_id": 15,
          "conf": 0.8465
        },
        {
          "text": "Total",
          "bbox": [
            78,
            690,
            163,
            713
          ],
          "line_id": 11,
          "block_id": 15,
          "conf": 0.985
        },
        {
          "text": "1488.62",
          "bbox": [
            1200,
            745,
            1306,
            764
          ],
          "line_id": 12,
          "block_id": 16,
          "conf": 0.8899
        },
        {
          "text": "Payment",
          "bbox": [
            79,
            746,
            193,
            771
          ],
          "line_id": 12,
          "block_id": 16,
          "conf": 0.8591
        },
        {
          "text": "Amount",
          "bbox": [
            201,
            746,
            297,
            771
          ],
          "line_id": 12,
          "block_id": 16,
          "conf": 0.9751
        }
      ]
    }
  ]
}
