{
  "pages": [
    {
      "page_index": 0,
      "width": 1600,
      "height": 2200,
      "tokens": [
        {
          "text": "Energy",
          "bbox": [
            744,
            68,
            913,
            116
          ],
          "line_id": 0,
          "block_id": 0,
          "conf": 0.872
        },
        {
          "text": "Group",
          "bbox": [
            931,
            68,
            1073,
            119
          ],
          "line_id": 0,
          "block_id": 0,
          "conf": 0.9706
        },
        {
          "text": "Ontario",
          "bbox": [
            528,
            72,
            729,
            119
          ],
          "line_id": 0,
          "block_id": 0,
          "conf": 0.846
        },
        {
          "text": "UTILITY",
          "bbox": [
            690,
            134,
            822,
            159
          ],
          "line_id": 1,
          "block_id": 1,
          "conf": 0.9019
        },
        {
          "text": "BILL",
          "bbox": [
            834,
            136,
            908,
            161
          ],
          "line_id": 1,
          "block_id": 1,
          "conf": 0.943
        },
        {
          "text": "Joe1",
          "bbox": [
            1155,
            198,
            1205,
            215
          ],
          "line_id": 2,
          "block_id": 3,
          "conf": 0.8663
        },
        {
          "text": "2025-06-27",
          "bbox": [
            382,
            198,
            509,
            219
          ],
          "line_id": 2,
          "block_id": 5,
          "conf": 0.9888
        },
        {
          "text": "6831",
          "bbox": [
            1099,
            201,
            1149,
            216
          ],
          "line_id": 2,
          "block_id": 3,
          "conf": 0.9185
        },
        {
          "text": "Date",
          "bbox": [
            204,
            199,
            259,
            219
          ],
          "line_id": 2,
          "block_id": 5,
          "conf": 0.9893
        },
        {
          "text": "Road",
          "bbox": [
            1213,
            199,
            1265,
            219
          ],
          "line_id": 2,
          "block_id": 3,
          "conf": 0.8503
        },
        {
          "text": "Statement",
          "bbox": [
            80,
            202,
            196,
            221
          ],
          "line_id": 2,
          "block_id": 5,
          "conf": 0.9134
        },
        {
          "text": "32904",
          "bbox": [
            1255,
            232,
            1322,
            252
          ],
          "line_id": 3,
          "block_id": 4,
          "conf": 0.85
        },
        {
          "text": "John,",
          "bbox": [
            1145,
            232,
            1214,
            253
          ],
          "line_id": 3,
          "block_id": 4,
          "conf": 0.8535
        },
        {
          "text": "KS",
          "bbox": [
            1222,
            232,
            1247,
            253
          ],
          "line_id": 3,
          "block_id": 4,
          "conf": 0.9236
        },
        {
          "text": "New",
          "bbox": [
            1098,
            234,
            1140,
            253
          ],
          "line_id": 3,
          "block_id": 4,
          "conf": 0.8296
        },
        {
          "text": "Due",
          "bbox": [
            82,
            235,
            123,
            254
          ],
          "line_id": 3,
          "block_id": 6,
          "conf": 0.927
        },
        {
          "text": "Date",
          "bbox": [
            128,
            235,
            187,
            254
          ],
          "line_id": 3,
          "block_id": 6,
          "conf": 0.8646
        },
        {
          "text": "2025-07-16",
          "bbox": [
            378,
            236,
            512,
            253
          ],
          "line_id": 3,
          "block_id": 6,
          "conf": 0.8754
        },
        {
          "text": "Number",
          "bbox": [
            189,
            271,
            275,
            287
          ],
          "line_id": 4,
          "block_id": 7,
          "conf": 0.8429
        },
        {
          "text": "6494999067",
          "bbox": [
            382,
            270,
            518,
            288
          ],
          "line_id": 4,
          "block_id": 7,
          "conf": 0.8244
        },
        {
          "text": "Account",
          "bbox": [
            78,
            272,
            180,
            290
          ],
          "line_id": 4,
          "block_id": 7,
          "conf": 0.878
        },
        {
          "text": "Bill",
          "bbox": [
            82,
            343,
            131,
            367
          ],
          "line_id": 5,
          "block_id": 9,
          "conf": 0.8377
        },
        {
          "text": "To",
          "bbox": [
            140,
            346,
            164,
            364
          ],
          "line_id": 5,
          "block_id": 9,
          "conf": 0.8476
        },
        {
          "text": "Misty",
          "bbox": [
            79,
            383,
            167,
            415
          ],
          "line_id": 6,
          "block_id": 10,
          "conf": 0.936
        },
        {
          "text": "Harper",
          "bbox": [
            173,
            385,
            274,
            414
          ],
          "line_id": 6,
          "block_id": 10,
          "conf": 0.9518
        },
        {
          "text": "Club",
          "bbox": [
            330,
            424,
            390,
            452
          ],
          "line_id": 7,
          "block_id": 11,
          "conf": 0.8227
        },
        {
          "text": "01A,",
          "bbox": [
            176,
            427,
            236,
            451
          ],
          "line_id": 7,
          "block_id": 11,
          "conf": 0.9564
        },
        {
          "text": "Ricky",
          "bbox": [
            247,
            426,
            321,
            452
          ],
          "line_id": 7,
          "block_id": 11,
          "conf": 0.9755
        },
        {
          "text": "Studio",
          "bbox": [
            80,
            426,
            169,
            455
          ],
          "line_id": 7,
          "block_id": 11,
          "conf": 0.8327
        },
        {
          "text": "6BZ",
          "bbox": [
            395,
            461,
            447,
            487
          ],
          "line_id": 8,
          "block_id": 12,
          "conf": 0.8384
        },
        {
          "text": "East",
          "bbox": [
            81,
            463,
            145,
            487
          ],
          "line_id": 8,
          "block_id": 12,
          "conf": 0.9345
        },
        {
          "text": "TW40",
          "bbox": [
            326,
            463,
            387,
            490
          ],
          "line_id": 8,
          "block_id": 12,
          "conf": 0.8236
        },
        {
          "text": "Lindatown,",
          "bbox": [
            154,
            465,
            313,
            491
          ],
          "line_id": 8,
          "block_id": 12,
          "conf": 0.8928
        },
        {
          "text": "United",
          "bbox": [
            78,
            502,
            175,
            527
          ],
          "line_id": 9,
          "block_id": 13,
          "conf": 0.8405
        },
        {
          "text": "Kingdom",
          "bbox": [
            184,
            502,
            297,
            529
          ],
          "line_id": 9,
          "block_id": 13,
          "conf": 0.9852
        },
        {
          "text": "AMOUNT",
          "bbox": [
            1301,
            575,
            1417,
            593
          ],
          "line_id": 10,
          "block_id": 15,
          "conf": 0.9518
        },
        {
          "text": "DESCRIPTION",
          "bbox": [
            79,
            576,
            256,
            594
          ],
          "line_id": 10,
          "block_id": 15,
          "conf": 0.9631
        },
        {
          "text": "177.65",
          "bbox": [
            1302,
            639,
            1388,
            660
          ],
          "line_id": 11,
          "block_id": 17,
          "conf": 0.9435
        },
        {
          "text": "PreviousBalance",
          "bbox": [
            78,
            640,
            300,
            662
          ],
          "line_id": 11,
          "block_id": 17,
          "conf": 0.8838
        },
        {
          "text": "203.73",
          "bbox": [
            1302,
            690,
            1389,
            710
          ],
          "line_id": 12,
          "block_id": 18,
          "conf": 0.9366
        },
        {
          "text": "Charges",
          "bbox": [
            188,
            690,
            289,
            715
          ],
          "line_id": 12,
          "block_id": 18,
          "conf": 0.9421
        },
        {
          "text": "Current",
          "bbox": [
            79,
            692,
            180,
            719
          ],
          "line_id": 12,
          "block_id": 18,
          "conf": 0.8561
        },
        {
          "text": "Service",
          "bbox": [
            82,
            741,
            180,
            758
          ],
          "line_id": 13,
          "block_id": 19,
          "conf": 0.8951
        },
        {
          "text": "Fee",
          "bbox": [
            187,
            738,
            232,
            762
          ],
          "line_id": 13,
          "block_id": 19,
          "conf": 0.9232
        },
        {
          "text": "2.50",
          "bbox": [
            1300,
            741,
            1358,
            759
          ],
          "line_id": 13,
          "block_id": 19,
          "conf": 0.8734
        },
        {
          "text": "Taxes",
          "bbox": [
            79,
            788,
            154,
            809
          ],
          "line_id": 14,
          "block_id": 20,
          "conf": 0.8786
        },
        {
          "text": "1.80",
          "bbox": [
            1302,
            789,
            1356,
            808
          ],
          "line_id": 14,
          "block_id": 20,
          "conf": 0.8411
        },
        {
          "text": "&",
          "bbox": [
            163,
            789,
            177,
            812
          ],
          "line_id": 14,
          "block_id": 20,
          "conf": 0.8418
        },
        {
          "text": "Levies",
          "bbox": [
            184,
            791,
            272,
            811
          ],
          "line_id": 14,
          "block_id": 20,
          "conf": 0.9306
        },
        {
          "text": "203.73",
          "bbox": [
            1299,
            868,
            1398,
            893
          ],
          "line_id": 15,
          "block_id": 22,
          "conf": 0.8386
        },
        {
          "text": "TOTAL",
          "bbox": [
            80,
            870,
            190,
            894
          ],
          "line_id": 15,
          "block_id": 22,
          "conf": 0.9648
        },
        {
          "text": "DUE",
          "bbox": [
            200,
            872,
            266,
            895
          ],
          "line_id": 15,
          "block_id": 22,
          "conf": 0.9842
        }
      ]
    }
  ]
}
